lumen_tooling/__init__.py
lumen_tooling/client.py
lumen_tooling/constants.py
lumen_tooling/models.py
lumen_tooling/tool_function.py
lumen_tooling/exceptions/__init__.py
lumen_tooling/exceptions/exceptions.py
lumen_tooling/http/__init__.py
lumen_tooling/http/_http_constants.py
lumen_tooling/http/base.py
lumen_tooling/managers/__init__.py
lumen_tooling/managers/provider.py
lumen_tooling/managers/tools.py
lumen_tooling/managers/triggers.py
lumen_tooling-1.0.5.dist-info/METADATA
lumen_tooling-1.0.5.dist-info/WHEEL
lumen_tooling-1.0.5.dist-info/top_level.txt
lumen_tooling-1.0.5.dist-info/RECORD
